{
  "finali": {
    "prefix": ["finali"],
    "body": [
      "<?php",
      "",
      "declare(strict_types=1);",
      "",
      "namespace ${VIM:BuildPhpNamespace()};",
      "",
      "final class ${VIM:expand('%:t:r')} implements ${VIM:expand('%:t:r')}Interface",
      "{",
      "\t$0",
      "}"
    ],
    "description": "Class definition template."
  },
  "final": {
    "prefix": ["final"],
    "body": [
      "<?php",
      "",
      "declare(strict_types=1);",
      "",
      "namespace ${VIM:BuildPhpNamespace()};",
      "",
      "final class ${VIM:expand('%:t:r')}",
      "{",
      "\t$0",
      "}"
    ],
    "description": "Final Class without interface definition template."
  },
  "interface": {
    "prefix": ["interface"],
    "body": [
      "<?php",
      "",
      "declare(strict_types=1);",
      "",
      "namespace ${VIM:BuildPhpNamespace()};",
      "",
      "interface ${VIM:expand('%:t:r')}",
      "{",
      "\t$0",
      "}"
    ],
    "description": "Interface"
  },
  "construct": {
    "prefix": ["construct"],
    "body": [
      "public function __construct (",
      "\t$1",
      ") {}"
    ],
    "description": "Construct definition template."
  },
  "static": {
    "prefix": ["static"],
    "body": [
      "public static function $1($2): $3",
      "{",
      "\t$0",
      "}"
    ],
    "description": "Public static method definition template."
  },
  "invoke": {
    "prefix": ["invoke"],
    "body": [
      "public function __invoke(): $1",
      "{",
      "\t$0",
      "}"
    ],
    "description": "Public invoke method definition template."
  },
  "public": {
    "prefix": ["public"],
    "body": [
      "public function $1($2): $3",
      "{",
      "\t$0",
      "}"
    ],
    "description": "Public method definition template."
  },
  "private": {
    "prefix": ["private"],
    "body": [
      "private function $1($2): $3",
      "{",
      "\t$0",
      "}"
    ],
    "description": "Private method definition template."
  },
  "namespace": {
    "prefix": ["namespace"],
    "body": [
      "namespace ${VIM:BuildPhpNamespace()};"
    ],
    "description": "Namespace template."
  },
  "className": {
    "prefix": ["className"],
    "body": [
      "${VIM:expand('%:t:r')}"
    ],
    "description": "Class name template."
  }
}
